{"content":[{"id":"7960cafc","settings":{"flex_direction":"column","boxed_width":{"unit":"px","size":1600,"sizes":[]},"padding":{"unit":"px","top":"0","right":"10","bottom":"30","left":"10","isLinked":false},"ekit_section_parallax_multi_items":[],"padding_tablet":{"unit":"px","top":"0","right":"0","bottom":"0","left":"0","isLinked":true},"background_background":"classic","__globals__":{"background_color":""},"pa_condition_repeater":[],"premium_tooltip_text":"Hi, I'm a global tooltip.","premium_tooltip_position":"top,bottom","premium_parallax_layers_list":[],"premium_gradient_colors_repeater":[],"premium_kenburns_repeater":[],"premium_lottie_repeater":[],"premium_blob_repeater":[],"pa_cursor_ftext":"Premium Follow Text","pa_badge_text":"New","ekit_all_conditions_list":[],"ekit_cursor_text_label":"Elementskit Cursor"},"elements":[{"id":"f1227cd","settings":{"flex_direction":"column","flex_gap":{"column":"20","row":"20","isLinked":true,"unit":"px","size":20},"flex_wrap":"wrap","background_background":"classic","border_radius":{"unit":"px","top":"40","right":"40","bottom":"40","left":"40","isLinked":true},"padding":{"unit":"px","top":"60","right":"10","bottom":"10","left":"10","isLinked":false},"ekit_section_parallax_multi_items":[],"__globals__":{"background_color":"globals\/colors?id=accent"},"flex_gap_tablet":{"column":"0","row":"0","isLinked":true,"unit":"px","size":0},"border_radius_tablet":{"unit":"px","top":"0","right":"0","bottom":"0","left":"0","isLinked":true},"padding_tablet":{"unit":"px","top":"50","right":"10","bottom":"10","left":"10","isLinked":false},"padding_mobile":{"unit":"px","top":"40","right":"10","bottom":"10","left":"10","isLinked":false},"ekit_particles_enable":"yes","ekit_particles_options":"file","ekit_particles_file":{"url":"https:\/\/rocketbookkeeper.com\/wp-content\/uploads\/2024\/05\/particlesjs-config-3.json","id":5926,"size":"","alt":"","source":"library"},"pa_condition_repeater":[],"premium_tooltip_text":"Hi, I'm a global tooltip.","premium_tooltip_position":"top,bottom","premium_parallax_layers_list":[],"premium_gradient_colors_repeater":[],"premium_kenburns_repeater":[],"premium_lottie_repeater":[],"premium_blob_repeater":[],"pa_cursor_ftext":"Premium Follow Text","pa_badge_text":"New","ekit_all_conditions_list":[],"ekit_cursor_text_label":"Elementskit Cursor"},"elements":[{"id":"6d1a2432","settings":{"flex_direction":"row","flex_gap":{"column":"0","row":"0","isLinked":true,"unit":"px","size":0},"flex_wrap":"wrap","padding":{"unit":"px","top":"0","right":"0","bottom":"0","left":"0","isLinked":true},"ekit_section_parallax_multi_items":[],"margin":{"unit":"px","top":"0","right":"0","bottom":"10","left":"0","isLinked":false},"pa_condition_repeater":[],"premium_tooltip_text":"Hi, I'm a global tooltip.","premium_tooltip_position":"top,bottom","premium_parallax_layers_list":[],"premium_gradient_colors_repeater":[],"premium_kenburns_repeater":[],"premium_lottie_repeater":[],"premium_blob_repeater":[],"pa_cursor_ftext":"Premium Follow Text","pa_badge_text":"New","ekit_all_conditions_list":[],"ekit_cursor_text_label":"Elementskit Cursor"},"elements":[{"id":"b8d96bc","settings":{"content_width":"full","width":{"unit":"%","size":42,"sizes":[]},"flex_direction":"column","ekit_section_parallax_multi_items":[],"width_tablet":{"unit":"%","size":100,"sizes":[]},"width_mobile":{"unit":"%","size":"","sizes":[]},"pa_condition_repeater":[],"premium_tooltip_text":"Hi, I'm a global tooltip.","premium_tooltip_position":"top,bottom","premium_parallax_layers_list":[],"premium_gradient_colors_repeater":[],"premium_kenburns_repeater":[],"premium_lottie_repeater":[],"premium_blob_repeater":[],"pa_cursor_ftext":"Premium Follow Text","pa_badge_text":"New","ekit_all_conditions_list":[],"ekit_cursor_text_label":"Elementskit Cursor"},"elements":[{"id":"7b844143","settings":{"image":{"url":"https:\/\/rocketbookkeeper.com\/wp-content\/uploads\/2024\/05\/Rocket-Bookkeeper-White-PNG-LOGO.png","id":6135,"size":"","alt":"","source":"library"},"image_size":"full","align":"left","space":{"unit":"%","size":100,"sizes":[]},"ekit_adv_tooltip_content":"Tooltip Content.","width_mobile":{"unit":"%","size":100,"sizes":[]},"space_mobile":{"unit":"px","size":150,"sizes":[]},"pa_condition_repeater":[],"premium_tooltip_text":"Hi, I'm a global tooltip.","premium_tooltip_position":"top,bottom","ekit_all_conditions_list":[],"pa_cursor_ftext":"Premium Follow Text","pa_badge_text":"New","premium_mscroll_repeater":[],"ekit_cursor_text_label":"Elementskit Cursor"},"elements":[],"isInner":false,"widgetType":"image","elType":"widget"}],"isInner":true,"elType":"container"},{"id":"53e5112","settings":{"content_width":"full","width":{"unit":"%","size":58,"sizes":[]},"flex_direction":"column","ekit_section_parallax_multi_items":[],"width_tablet":{"unit":"%","size":100,"sizes":[]},"width_mobile":{"unit":"%","size":"","sizes":[]},"pa_condition_repeater":[],"premium_tooltip_text":"Hi, I'm a global tooltip.","premium_tooltip_position":"top,bottom","premium_parallax_layers_list":[],"premium_gradient_colors_repeater":[],"premium_kenburns_repeater":[],"premium_lottie_repeater":[],"premium_blob_repeater":[],"pa_cursor_ftext":"Premium Follow Text","pa_badge_text":"New","ekit_all_conditions_list":[],"ekit_cursor_text_label":"Elementskit Cursor"},"elements":[{"id":"22bdbdb6","settings":{"title":"Online Bookkeeping Powered by Real Humans","align":"left","ekit_adv_tooltip_content":"Tooltip Content.","__globals__":{"title_color":"globals\/colors?id=24250ce","typography_typography":"globals\/typography?id=primary"},"title_color":"#FFFFFF","pa_condition_repeater":[],"premium_tooltip_text":"Hi, I'm a global tooltip.","premium_tooltip_position":"top,bottom","ekit_all_conditions_list":[],"pa_cursor_ftext":"Premium Follow Text","pa_badge_text":"New","premium_mscroll_repeater":[],"ekit_cursor_text_label":"Elementskit Cursor"},"elements":[],"isInner":false,"widgetType":"heading","elType":"widget"}],"isInner":true,"elType":"container"}],"isInner":true,"elType":"container"},{"id":"52ff6a7d","settings":{"flex_direction":"row","flex_gap":{"column":"0","row":"0","isLinked":true,"unit":"px","size":0},"flex_wrap":"wrap","padding":{"unit":"px","top":"0","right":"0","bottom":"0","left":"0","isLinked":true},"ekit_section_parallax_multi_items":[],"margin":{"unit":"px","top":"0","right":"0","bottom":"35","left":"0","isLinked":false},"flex_gap_tablet":{"column":"0","row":"0","isLinked":true,"unit":"px","size":0},"margin_tablet":{"unit":"px","top":"0","right":"0","bottom":"15","left":"0","isLinked":false},"margin_mobile":{"unit":"px","top":"0","right":"0","bottom":"30","left":"0","isLinked":false},"pa_condition_repeater":[],"premium_tooltip_text":"Hi, I'm a global tooltip.","premium_tooltip_position":"top,bottom","premium_parallax_layers_list":[],"premium_gradient_colors_repeater":[],"premium_kenburns_repeater":[],"premium_lottie_repeater":[],"premium_blob_repeater":[],"pa_cursor_ftext":"Premium Follow Text","pa_badge_text":"New","ekit_all_conditions_list":[],"ekit_cursor_text_label":"Elementskit Cursor"},"elements":[{"id":"b8aae9b","settings":{"content_width":"full","width":{"unit":"%","size":42,"sizes":[]},"ekit_section_parallax_multi_items":[],"width_tablet":{"unit":"%","size":100,"sizes":[]},"width_mobile":{"unit":"%","size":"","sizes":[]},"margin_tablet":{"unit":"px","top":"0","right":"0","bottom":"10","left":"0","isLinked":false},"pa_condition_repeater":[],"premium_tooltip_text":"Hi, I'm a global tooltip.","premium_tooltip_position":"top,bottom","premium_parallax_layers_list":[],"premium_gradient_colors_repeater":[],"premium_kenburns_repeater":[],"premium_lottie_repeater":[],"premium_blob_repeater":[],"pa_cursor_ftext":"Premium Follow Text","pa_badge_text":"New","ekit_all_conditions_list":[],"ekit_cursor_text_label":"Elementskit Cursor"},"elements":[{"id":"51712b85","settings":{"title":"Newsletter Signup","header_size":"h3","align":"left","title_color":"#FFFFFF","typography_typography":"custom","typography_font_size":{"unit":"px","size":24,"sizes":[]},"typography_font_size_tablet":{"unit":"px","size":22,"sizes":[]},"typography_font_size_mobile":{"unit":"px","size":20,"sizes":[]},"typography_line_height":{"unit":"em","size":1.1,"sizes":[]},"typography_letter_spacing":{"unit":"em","size":-0.03,"sizes":[]},"ekit_adv_tooltip_content":"Tooltip Content.","__globals__":{"title_color":"globals\/colors?id=24250ce","typography_typography":""},"_margin":{"unit":"px","top":"0","right":"0","bottom":"10","left":"0","isLinked":false},"_margin_mobile":{"unit":"px","top":"0","right":"0","bottom":"0","left":"0","isLinked":true},"pa_condition_repeater":[],"premium_tooltip_text":"Hi, I'm a global tooltip.","premium_tooltip_position":"top,bottom","ekit_all_conditions_list":[],"pa_cursor_ftext":"Premium Follow Text","pa_badge_text":"New","premium_mscroll_repeater":[],"ekit_cursor_text_label":"Elementskit Cursor"},"elements":[],"isInner":false,"widgetType":"heading","elType":"widget"},{"id":"466f0306","settings":{"form_name":"New Form","form_fields":[{"custom_id":"email","field_type":"email","required":"true","placeholder":"Enter Your Emal","width":"50","_id":"763912c"}],"button_width":"70","step_next_label":"Next","step_previous_label":"Previous","button_text":"Subscribe Now","email_content":"[all-fields]","email_content_2":"[all-fields]","success_message":"Your submission was successful.","error_message":"Your submission failed because of an error.","server_message":"Your submission failed because of a server error.","invalid_message":"Your submission failed because the form is invalid.","required_field_message":"This field is required.","ekit_google_sheet_enable":"","column_gap":{"unit":"px","size":12,"sizes":[]},"row_gap":{"unit":"px","size":16,"sizes":[]},"field_background_color":"#F5F7FA","button_align":"start","button_content_align":"start","button_background_color":"#7393B3","button_background_hover_color":"#FFFFFF","previous_button_background_color_hover":"#191970","success_message_color":"#FFFFFF","error_message_color":"#FFFFFF","ekit_all_conditions_list":[],"ekit_adv_tooltip_content":"Tooltip Content.","ekit_cursor_text_label":"Elementskit Cursor","__globals__":{"button_background_color":"globals\/colors?id=primary","field_background_color":"","button_hover_color":"globals\/colors?id=accent","previous_button_background_color_hover":"globals\/colors?id=accent","button_background_hover_color":""},"pa_condition_repeater":[],"premium_tooltip_text":"Hi, I'm a global tooltip.","premium_tooltip_position":"top,bottom","pa_cursor_ftext":"Premium Follow Text","pa_badge_text":"New","premium_mscroll_repeater":[]},"elements":[],"isInner":false,"widgetType":"form","elType":"widget"}],"isInner":true,"elType":"container"},{"id":"6c173188","settings":{"content_width":"full","width":{"unit":"%","size":19,"sizes":[]},"ekit_section_parallax_multi_items":[],"width_tablet":{"unit":"%","size":33.33,"sizes":[]},"width_mobile":{"unit":"%","size":50,"sizes":[]},"pa_condition_repeater":[],"premium_tooltip_text":"Hi, I'm a global tooltip.","premium_tooltip_position":"top,bottom","premium_parallax_layers_list":[],"premium_gradient_colors_repeater":[],"premium_kenburns_repeater":[],"premium_lottie_repeater":[],"premium_blob_repeater":[],"pa_cursor_ftext":"Premium Follow Text","pa_badge_text":"New","ekit_all_conditions_list":[],"ekit_cursor_text_label":"Elementskit Cursor"},"elements":[{"id":"5abea529","settings":{"title":"Quick Links","header_size":"h3","align":"left","ekit_adv_tooltip_content":"Tooltip Content.","__globals__":{"title_color":"globals\/colors?id=24250ce","typography_typography":""},"title_color":"#FFFFFF","typography_typography":"custom","typography_font_size":{"unit":"px","size":22,"sizes":[]},"typography_font_size_tablet":{"unit":"px","size":20,"sizes":[]},"typography_font_size_mobile":{"unit":"px","size":20,"sizes":[]},"typography_line_height":{"unit":"em","size":1.1,"sizes":[]},"typography_letter_spacing":{"unit":"em","size":-0.03,"sizes":[]},"pa_condition_repeater":[],"premium_tooltip_text":"Hi, I'm a global tooltip.","premium_tooltip_position":"top,bottom","ekit_all_conditions_list":[],"pa_cursor_ftext":"Premium Follow Text","pa_badge_text":"New","premium_mscroll_repeater":[],"ekit_cursor_text_label":"Elementskit Cursor"},"elements":[],"isInner":false,"widgetType":"heading","elType":"widget"},{"id":"432a6052","settings":{"elementskit_nav_menu":"footer-menu","elementskit_vertical_menu_toggle_title":"All Categories","ekit_vertical_menu_container_background_background":"classic","ekit_vertical_menu_container_background_color":"#FFFFFF00","ekit_vertical_menu_items_padding":{"unit":"px","top":"0","right":"0","bottom":"15","left":"0","isLinked":false},"ekit_vertical_menu_items_icon_padding":{"unit":"px","top":"0","right":"0","bottom":"0","left":"0","isLinked":true},"ekit_vertical_menu_items_border_border":"none","ekit_vertical_sub_menu_items_border_border":"none","ekit_adv_tooltip_content":"Tooltip Content.","__globals__":{"ekit_vertical_menu_container_background_color":"","ekit_vertical_menu_items_content_typography_typography":"globals\/typography?id=text","ekit_vertical_menu_items_title_color":"globals\/colors?id=24250ce","ekit_vertical_sub_menu_items_content_typography_typography":"globals\/typography?id=text","ekit_vertical_sub_menu_items_title_color":"globals\/colors?id=secondary","ekit_vertical_menu_items_title_color_active":"globals\/colors?id=primary"},"ekit_vertical_menu_container_box_shadow_box_shadow_type":"yes","ekit_vertical_menu_container_box_shadow_box_shadow":{"horizontal":0,"vertical":0,"blur":0,"spread":0,"color":"rgba(0,0,0,0.5)"},"pa_condition_repeater":[],"premium_tooltip_text":"Hi, I'm a global tooltip.","premium_tooltip_position":"top,bottom","ekit_all_conditions_list":[],"pa_cursor_ftext":"Premium Follow Text","pa_badge_text":"New","premium_mscroll_repeater":[],"ekit_cursor_text_label":"Elementskit Cursor"},"elements":[],"isInner":false,"widgetType":"ekit-vertical-menu","elType":"widget"}],"isInner":true,"elType":"container"},{"id":"5831a67","settings":{"content_width":"full","width":{"unit":"%","size":13.664},"ekit_section_parallax_multi_items":[],"width_tablet":{"unit":"%","size":33.33,"sizes":[]},"width_mobile":{"unit":"%","size":50,"sizes":[]},"pa_condition_repeater":[],"premium_tooltip_text":"Hi, I'm a global tooltip.","premium_tooltip_position":"top,bottom","premium_parallax_layers_list":[],"premium_gradient_colors_repeater":[],"premium_kenburns_repeater":[],"premium_lottie_repeater":[],"premium_blob_repeater":[],"pa_cursor_ftext":"Premium Follow Text","pa_badge_text":"New","ekit_all_conditions_list":[],"ekit_cursor_text_label":"Elementskit Cursor","_flex_size":"none","_element_width":"initial"},"elements":[{"id":"4fa40502","settings":{"title":"Socials","header_size":"h3","align":"left","ekit_adv_tooltip_content":"Tooltip Content.","__globals__":{"title_color":"globals\/colors?id=24250ce","typography_typography":""},"title_color":"#FFFFFF","typography_typography":"custom","typography_font_size":{"unit":"px","size":22,"sizes":[]},"typography_font_size_tablet":{"unit":"px","size":20,"sizes":[]},"typography_font_size_mobile":{"unit":"px","size":20,"sizes":[]},"typography_line_height":{"unit":"em","size":1.1,"sizes":[]},"typography_letter_spacing":{"unit":"em","size":-0.03,"sizes":[]},"pa_condition_repeater":[],"premium_tooltip_text":"Hi, I'm a global tooltip.","premium_tooltip_position":"top,bottom","ekit_all_conditions_list":[],"pa_cursor_ftext":"Premium Follow Text","pa_badge_text":"New","premium_mscroll_repeater":[],"ekit_cursor_text_label":"Elementskit Cursor"},"elements":[],"isInner":false,"widgetType":"heading","elType":"widget"},{"id":"402b6a0a","settings":{"icon_list":[{"text":"Linkedin","selected_icon":{"value":"fab fa-linkedin","library":"fa-brands"},"_id":"a12abff","link":{"url":"https:\/\/www.linkedin.com\/company\/rocket-bookkeeper\/","is_external":"","nofollow":"","custom_attributes":""}}],"icon_size":{"unit":"px","size":25,"sizes":[]},"ekit_all_conditions_list":[],"ekit_adv_tooltip_content":"Tooltip Content.","pa_condition_repeater":[],"premium_tooltip_text":"Hi, I'm a global tooltip.","premium_tooltip_position":"top,bottom","pa_cursor_ftext":"Premium Follow Text","pa_badge_text":"New","premium_mscroll_repeater":[],"ekit_cursor_text_label":"Elementskit Cursor","__globals__":{"icon_color":"globals\/colors?id=secondary"}},"elements":[],"isInner":false,"widgetType":"icon-list","elType":"widget"}],"isInner":true,"elType":"container"},{"id":"457483dc","settings":{"content_width":"full","width":{"unit":"%","size":20,"sizes":[]},"ekit_section_parallax_multi_items":[],"width_tablet":{"unit":"%","size":33.33,"sizes":[]},"width_mobile":{"unit":"%","size":"","sizes":[]},"pa_condition_repeater":[],"premium_tooltip_text":"Hi, I'm a global tooltip.","premium_tooltip_position":"top,bottom","premium_parallax_layers_list":[],"premium_gradient_colors_repeater":[],"premium_kenburns_repeater":[],"premium_lottie_repeater":[],"premium_blob_repeater":[],"pa_cursor_ftext":"Premium Follow Text","pa_badge_text":"New","ekit_all_conditions_list":[],"ekit_cursor_text_label":"Elementskit Cursor"},"elements":[{"id":"89555ca","settings":{"title":"Say Hello","header_size":"h3","align":"left","ekit_adv_tooltip_content":"Tooltip Content.","__globals__":{"title_color":"globals\/colors?id=24250ce","typography_typography":""},"title_color":"#FFFFFF","typography_typography":"custom","typography_font_size":{"unit":"px","size":22,"sizes":[]},"typography_font_size_tablet":{"unit":"px","size":20,"sizes":[]},"typography_font_size_mobile":{"unit":"px","size":20,"sizes":[]},"typography_line_height":{"unit":"em","size":1.1,"sizes":[]},"typography_letter_spacing":{"unit":"em","size":-0.03,"sizes":[]},"pa_condition_repeater":[],"premium_tooltip_text":"Hi, I'm a global tooltip.","premium_tooltip_position":"top,bottom","ekit_all_conditions_list":[],"pa_cursor_ftext":"Premium Follow Text","pa_badge_text":"New","premium_mscroll_repeater":[],"ekit_cursor_text_label":"Elementskit Cursor"},"elements":[],"isInner":false,"widgetType":"heading","elType":"widget"},{"id":"29d6acce","settings":{"icon_list":[{"text":"contact@rocketbookkeeper.com","selected_icon":{"value":"","library":""},"_id":"76dd43e","link":{"url":"mailto:contact@rocketbookkeeper.com","is_external":"","nofollow":"","custom_attributes":""}},{"text":"(332) 378-6724","selected_icon":{"value":"","library":""},"_id":"238a8a5","link":{"url":"tel:+13323786724","is_external":"","nofollow":"","custom_attributes":""}},{"_id":"b383760","text":"140 Broadway, New York, NY 10005, United States","selected_icon":{"value":"","library":""}}],"space_between":{"unit":"px","size":15,"sizes":[]},"icon_size":{"unit":"px","size":16,"sizes":[]},"icon_self_align":"left","icon_self_vertical_align":"flex-start","icon_vertical_offset":{"unit":"px","size":6,"sizes":[]},"ekit_adv_tooltip_content":"Tooltip Content.","__globals__":{"icon_color":"","icon_typography_typography":"globals\/typography?id=text","text_color_hover":"globals\/colors?id=secondary"},"icon_color":"#0000FC","icon_typography_typography":"custom","icon_typography_font_family":"Plus Jakarta Sans","icon_typography_font_size":{"unit":"px","size":16,"sizes":[]},"icon_typography_font_size_tablet":{"unit":"px","size":16,"sizes":[]},"icon_typography_font_size_mobile":{"unit":"px","size":16,"sizes":[]},"icon_typography_font_weight":"400","icon_typography_line_height":{"unit":"em","size":1.6,"sizes":[]},"text_color_hover":"#F5F7FA","pa_condition_repeater":[],"premium_tooltip_text":"Hi, I'm a global tooltip.","premium_tooltip_position":"top,bottom","ekit_all_conditions_list":[],"pa_cursor_ftext":"Premium Follow Text","pa_badge_text":"New","premium_mscroll_repeater":[],"ekit_cursor_text_label":"Elementskit Cursor"},"elements":[],"isInner":false,"widgetType":"icon-list","elType":"widget"},{"id":"4c9df753","settings":{"content_width":"full","ekit_btn_text":"Book Now","ekit_btn_url":{"url":"https:\/\/rocketbookkeeper.com\/book-now\/","is_external":"","nofollow":"","custom_attributes":""},"ekit_btn_text_padding":{"unit":"px","top":"12","right":"20","bottom":"12","left":"20","isLinked":false},"ekit_btn_typography_typography":"custom","ekit_btn_typography_font_size":{"unit":"px","size":16,"sizes":[]},"ekit_btn_typography_font_size_tablet":{"unit":"px","size":20,"sizes":[]},"ekit_btn_typography_font_size_mobile":{"unit":"px","size":18,"sizes":[]},"ekit_btn_typography_font_weight":"700","ekit_btn_typography_line_height":{"unit":"em","size":1.2,"sizes":[]},"ekit_btn_typography_letter_spacing":{"unit":"em","size":0.01,"sizes":[]},"ekit_btn_text_color":"#FFFFFF","ekit_btn_bg_color":"#7393B3","ekit_btn_hover_color":"#191970","ekit_btn_bg_hover_color":"#F5F7FA","ekit_btn_bg_border_radius":{"unit":"px","top":"8","right":"8","bottom":"8","left":"8","isLinked":true},"_flex_align_self":"flex-start","ekit_adv_tooltip_content":"Tooltip Content.","__globals__":{"ekit_btn_text_color":"globals\/colors?id=24250ce","ekit_btn_bg_color":"globals\/colors?id=e1d4eee","ekit_btn_typography_typography":"","ekit_btn_hover_color":"globals\/colors?id=accent","ekit_btn_bg_hover_color":"globals\/colors?id=secondary","ekit_btn_bg_hover_slide_bg_color":""},"pa_condition_repeater":[],"premium_tooltip_text":"Hi, I'm a global tooltip.","premium_tooltip_position":"top,bottom","ekit_all_conditions_list":[],"pa_cursor_ftext":"Premium Follow Text","pa_badge_text":"New","premium_mscroll_repeater":[],"ekit_cursor_text_label":"Elementskit Cursor"},"elements":[],"isInner":false,"widgetType":"elementskit-creative-button","elType":"widget"}],"isInner":true,"elType":"container"}],"isInner":true,"elType":"container"},{"id":"6e4db004","settings":{"flex_direction":"column","flex_gap":{"column":"0","row":"0","isLinked":true,"unit":"px","size":0},"flex_wrap":"wrap","border_border":"solid","border_width":{"unit":"px","top":"1","right":"0","bottom":"0","left":"0","isLinked":false},"padding":{"unit":"px","top":"30","right":"10","bottom":"20","left":"10","isLinked":false},"ekit_section_parallax_multi_items":[],"__globals__":{"border_color":"globals\/colors?id=cdb7ec5"},"padding_tablet":{"unit":"px","top":"20","right":"10","bottom":"10","left":"10","isLinked":false},"content_width":"full","pa_condition_repeater":[],"premium_tooltip_text":"Hi, I'm a global tooltip.","premium_tooltip_position":"top,bottom","premium_parallax_layers_list":[],"premium_gradient_colors_repeater":[],"premium_kenburns_repeater":[],"premium_lottie_repeater":[],"premium_blob_repeater":[],"pa_cursor_ftext":"Premium Follow Text","pa_badge_text":"New","ekit_all_conditions_list":[],"ekit_cursor_text_label":"Elementskit Cursor"},"elements":[{"id":"6832924f","settings":{"editor":"<p>Copyright \u00a9 2025 Rocket Bookkeeper. All Rights Reserved.<\/p>","align":"center","ekit_adv_tooltip_content":"Tooltip Content.","__globals__":{"text_color":"globals\/colors?id=24250ce","typography_typography":"globals\/typography?id=text"},"pa_condition_repeater":[],"premium_tooltip_text":"Hi, I'm a global tooltip.","premium_tooltip_position":"top,bottom","ekit_all_conditions_list":[],"pa_cursor_ftext":"Premium Follow Text","pa_badge_text":"New","premium_mscroll_repeater":[],"ekit_cursor_text_label":"Elementskit Cursor"},"elements":[],"isInner":false,"widgetType":"text-editor","elType":"widget"}],"isInner":true,"elType":"container"}],"isInner":true,"elType":"container"}],"isInner":false,"elType":"container"}],"page_settings":{"pa_cursor_ftext":"Premium Follow Text"},"version":"0.4","title":"my footer 1","type":"container"}